chrome_version/__init__.py
chrome_version/__main__.py
chrome_version/_version.py
chrome_version/cli.py
chrome_version/core.py
chrome_version-0.4.0.dist-info/METADATA
chrome_version-0.4.0.dist-info/WHEEL
chrome_version-0.4.0.dist-info/entry_points.txt
chrome_version-0.4.0.dist-info/licenses/LICENSE
chrome_version-0.4.0.dist-info/RECORD
