Metadata-Version: 2.4
Name: chrome-version
Version: 0.4.0
Summary: Detect the version of Chrome installed on Windows, Linux, Mac. Cross-platform using Python, native OS detection.
Project-URL: changelog, https://github.com/hasansezertasan/chrome-version/blob/main/CHANGELOG.md
Project-URL: documentation, https://github.com/hasansezertasan/chrome-version#readme
Project-URL: homepage, https://github.com/hasansezertasan/chrome-version
Project-URL: issues, https://github.com/hasansezertasan/chrome-version/issues
Project-URL: releasenotes, https://github.com/hasansezertasan/chrome-version/releases
Project-URL: source, https://github.com/hasansezertasan/chrome-version.git
Author-email: Hasan Sezer Taşan <hasansezertasan@gmail.com>
Maintainer-email: Hasan Sezer Taşan <hasansezertasan@gmail.com>
License: MIT
License-File: LICENSE
Keywords: chrome,google,google chrome version,version
Classifier: Development Status :: 5 - Production/Stable
Classifier: Environment :: Console
Classifier: Intended Audience :: Developers
Classifier: License :: OSI Approved :: MIT License
Classifier: Operating System :: OS Independent
Classifier: Programming Language :: Python
Classifier: Programming Language :: Python :: 3
Classifier: Programming Language :: Python :: 3 :: Only
Classifier: Programming Language :: Python :: 3.5
Classifier: Programming Language :: Python :: 3.6
Classifier: Programming Language :: Python :: 3.7
Classifier: Programming Language :: Python :: 3.8
Classifier: Programming Language :: Python :: 3.9
Classifier: Programming Language :: Python :: 3.10
Classifier: Programming Language :: Python :: 3.11
Classifier: Programming Language :: Python :: 3.12
Classifier: Programming Language :: Python :: 3.13
Classifier: Programming Language :: Python :: 3.14
Classifier: Programming Language :: Python :: 3.15
Classifier: Topic :: Software Development :: Libraries :: Python Modules
Requires-Python: <4.0,>=3.0
